secretcli/__init__.py
secretcli/secretcli.py
secretcli-0.1.4.dist-info/LICENSE
secretcli-0.1.4.dist-info/METADATA
secretcli-0.1.4.dist-info/WHEEL
secretcli-0.1.4.dist-info/entry_points.txt
secretcli-0.1.4.dist-info/top_level.txt
secretcli-0.1.4.dist-info/RECORD
