Metadata-Version: 2.1
Name: secretcli
Version: 0.1.4
Summary: UNKNOWN
Home-page: https://github.com/tedivm/secretcli
Author: Robert Hafner
Author-email: tedivm@tedivm.com
License: UNKNOWN
Download-URL: https://github.com/tedivm/secretcli/archive/v0.1.4.tar.gz
Platform: UNKNOWN
Classifier: Development Status :: 4 - Beta
Classifier: License :: OSI Approved :: MIT License
Classifier: Intended Audience :: Developers
Classifier: Intended Audience :: System Administrators
Classifier: Programming Language :: Python :: 3
Classifier: Environment :: Console
Requires-Python: >=3
Requires-Dist: boto3 (<2.0,>=1.9)
Requires-Dist: click (<8.0,>=6.0)
Requires-Dist: requests
Requires-Dist: pyyaml
Requires-Dist: urllib3 (<1.24)
Provides-Extra: dev
Requires-Dist: pypandoc ; extra == 'dev'
Requires-Dist: twine ; extra == 'dev'
Requires-Dist: wheel ; extra == 'dev'
